gdalos/__init__.py
gdalos/__util__.py
gdalos/coord_resolution_tester.py
gdalos/empty_raster.py
gdalos/extent_utils_backport.py
gdalos/gdal2xyz.py
gdalos/gdal_write_array_to_file.py
gdalos/gdalos_base.py
gdalos/gdalos_color.py
gdalos/gdalos_extent.py
gdalos/gdalos_logger.py
gdalos/gdalos_main.py
gdalos/gdalos_selector.py
gdalos/gdalos_trans.py
gdalos/gdalos_types.py
gdalos/gdalos_util.py
gdalos/gdalos_versions.py
gdalos/gdalos_vrt.py
gdalos/partitions.py
gdalos/projdef.py
gdalos/rectangle.py
gdalos/scale_calc.py
gdalos/talos_osr.py
gdalos/test_data_generator.py
gdalos/util.py
gdalos/utm_convergence.py
gdalos/backports/__init__.py
gdalos/backports/ogr_utils.py
gdalos/backports/osr_util2.py
gdalos/backports/osr_utm_util.py
gdalos/calc/__init__.py
gdalos/calc/discrete_mode.py
gdalos/calc/gdal_calc.py
gdalos/calc/gdal_dem_color_cutline.py
gdalos/calc/gdal_to_czml.py
gdalos/calc/gdal_to_json.py
gdalos/calc/gdalos_comb_tests.py
gdalos/calc/gdalos_combine.py
gdalos/calc/gdalos_raster_color.py
gdalos/calc/get_pixel_from_raster.py
gdalos/calc/scale_raster.py
gdalos/rasterize/__init__.py
gdalos/rasterize/gdalos_rasterize.py
gdalos/talos/__init__.py
gdalos/talos/gen_consts.py
gdalos/talos/geom_arc.py
gdalos/talos/geom_util.py
gdalos/talos/math0.py
gdalos/talos/ogr_util.py
gdalos/viewshed/__init__.py
gdalos/viewshed/radio_params.py
gdalos/viewshed/refraction_coeff.py
gdalos/viewshed/talosgis_init.py
gdalos/viewshed/viewshed_calc.py
gdalos/viewshed/viewshed_grid_gdal.py
gdalos/viewshed/viewshed_grid_params.py
gdalos/viewshed/viewshed_grid_talos.py
gdalos/viewshed/viewshed_params.py
gdalos-0.64.1.data/scripts/gdalos_qt.bat
gdalos-0.64.1.data/scripts/gdalos_trans.bat
gdalos-0.64.1.data/scripts/gdalos_trans.py
gdalos_qt/__init__.py
gdalos_qt/__main__.py
gdalos_qt/crs_widget.py
gdalos_qt/gdalos_widget.py
gdalos_qt/nodatavalue_widget.py
gdalos-0.64.1.dist-info/LICENSE
gdalos-0.64.1.dist-info/METADATA
gdalos-0.64.1.dist-info/WHEEL
gdalos-0.64.1.dist-info/top_level.txt
gdalos-0.64.1.dist-info/RECORD
