Metadata-Version: 2.1
Name: gdalos
Version: 0.64.1
Summary: a simple gdal translate/warp/addo python wrapper for raster batch processing
Home-page: https://github.com/talos-gis/gdalos
Author: Idan Miara, Ben Avrahami
Author-email: idan@miara.com
License: MIT
Platform: UNKNOWN
Classifier: Development Status :: 5 - Production/Stable
Classifier: Intended Audience :: Developers
Classifier: Intended Audience :: Science/Research
Classifier: License :: OSI Approved :: MIT License
Classifier: Operating System :: OS Independent
Classifier: Programming Language :: Python :: 3
Classifier: Topic :: Scientific/Engineering :: GIS
Classifier: Topic :: Scientific/Engineering :: Information Analysis
Requires-Python: >=3.6.0
License-File: LICENSE
Requires-Dist: gdal (>=2.4.0)
Requires-Dist: gdal-utils (>=3.3.1)
Requires-Dist: numpy (!=1.19.4)
Provides-Extra: qt
Requires-Dist: fidget[qt] ; extra == 'qt'
Provides-Extra: rf
Requires-Dist: pyproj (>=3.1.0) ; extra == 'rf'
Requires-Dist: rfmodel (>=0.0.9) ; extra == 'rf'
